ipysigma/__init__.py
ipysigma/_frontend.py
ipysigma/_version.py
ipysigma/constants.py
ipysigma/gexf.py
ipysigma/grid.py
ipysigma/interfaces.py
ipysigma/shim.py
ipysigma/sigma.py
ipysigma/utils.py
ipysigma/labextension/build_log.json
ipysigma/labextension/package.json
ipysigma/labextension/static/_4b97.c50d29bbc3d9e8d566bf.js
ipysigma/labextension/static/_4b97.c50d29bbc3d9e8d566bf.js.map
ipysigma/labextension/static/lib_index_js.14ea78384dc208caf0d1.js
ipysigma/labextension/static/lib_index_js.14ea78384dc208caf0d1.js.map
ipysigma/labextension/static/lib_plugin_js.c8a13d00d8b43425ec0e.js
ipysigma/labextension/static/lib_plugin_js.c8a13d00d8b43425ec0e.js.map
ipysigma/labextension/static/lib_widget_js-data_image_svg_xml_base64_PHN2ZyB3aWR0aD0iMjEiIGhlaWdodD0iMjEiIHZpZXdCb3g9IjAgM-6426be.ab9d76b5cb61a52f9bf8.js
ipysigma/labextension/static/lib_widget_js-data_image_svg_xml_base64_PHN2ZyB3aWR0aD0iMjEiIGhlaWdodD0iMjEiIHZpZXdCb3g9IjAgM-6426be.ab9d76b5cb61a52f9bf8.js.map
ipysigma/labextension/static/node_modules_comma-number_index_js.b8778367abdcc556ac0a.js
ipysigma/labextension/static/node_modules_comma-number_index_js.b8778367abdcc556ac0a.js.map
ipysigma/labextension/static/node_modules_debounce_index_js.5f5b9fe7aeb86f291fd7.js
ipysigma/labextension/static/node_modules_debounce_index_js.5f5b9fe7aeb86f291fd7.js.map
ipysigma/labextension/static/node_modules_file-saver_dist_FileSaver_min_js.81fbff02713240ddb9d8.js
ipysigma/labextension/static/node_modules_file-saver_dist_FileSaver_min_js.81fbff02713240ddb9d8.js.map
ipysigma/labextension/static/node_modules_graphology-utils_getters_js-node_modules_graphology-utils_infer-type_js-node_mod-f34fd3.0ce686bfef6d97c918bb.js
ipysigma/labextension/static/node_modules_graphology-utils_getters_js-node_modules_graphology-utils_infer-type_js-node_mod-f34fd3.0ce686bfef6d97c918bb.js.map
ipysigma/labextension/static/node_modules_graphology-utils_is-graph_js.6478caec92bf44f65e6c.js
ipysigma-0.24.5.dist-info/LICENSE.txt
ipysigma-0.24.5.dist-info/METADATA
ipysigma-0.24.5.dist-info/WHEEL
ipysigma-0.24.5.dist-info/top_level.txt
ipysigma-0.24.5.dist-info/RECORD
