Metadata-Version: 2.1
Name: ipysigma
Version: 0.24.5
Summary: A Jupyter widget using sigma.js to render interactive networks.
Home-page: https://github.com/medialab/ipysigma
Author: Guillaume Plique
Author-email: guillaume.plique@sciencespo.fr
License: MIT
Keywords: Jupyter,Widgets,IPython,Sigma,graph
Platform: Linux
Platform: Mac OS X
Platform: Windows
Classifier: Intended Audience :: Developers
Classifier: Intended Audience :: Science/Research
Classifier: License :: OSI Approved :: BSD License
Classifier: Programming Language :: Python
Classifier: Programming Language :: Python :: 3
Classifier: Programming Language :: Python :: 3.4
Classifier: Programming Language :: Python :: 3.5
Classifier: Programming Language :: Python :: 3.6
Classifier: Programming Language :: Python :: 3.7
Classifier: Framework :: Jupyter
Requires-Python: >=3.6
License-File: LICENSE.txt
Requires-Dist: ipywidgets<9,>=7
Provides-Extra: examples
Provides-Extra: test
Requires-Dist: pytest>=4.6; extra == "test"
Requires-Dist: nbval; extra == "test"
